{
    "spriteSheet": "aztec",
    "backgrounds": [
        {
            "tile": "background",
            "intervals": [
                [
                    0, 200,
                    0, 25
                ]
            ]
        },
        {
            "tileA": "groundA",
            "tileB": "groundB",
            "intervals": [
                [
                    0, 16,
                    23, 24
                ]
            ]
        },
        {
            "tile": "underground",
            "intervals": [
                [
                    20, 200,
                    24, 25
                ]
            ]
        },

        {
            "tileA": "groundA",
            "tileB": "groundB",
            "intervals": [
                [
                    20, 200,
                    23, 24
                ]
            ]
        },
        {
            "tile": "underground",
            "intervals": [
                [
                    0, 16,
                    24, 25
                ]
            ]
        },

        {
            "tileA": "groundA",
            "tileB": "groundB",
            "intervals": [
                [
                    33, 45,
                    13, 14
                ]
            ]
        },
        {
            "tileA": "square11A",
            "tileB": "square11B",
            "intervals": [
                [
                    14, 16,
                    21, 22
                ]
            ]
        },
        {
            "tileA": "square11C",
            "tileB": "square11D",
            "intervals": [
                [
                    14, 16,
                    22, 23
                ]
            ]
        },

        {
            "tileA": "square31A",
            "tileB": "square31B",
            "intervals": [
                [
                    20, 24,
                    21, 22
                ]
            ]
        },
        {
            "tileA": "square31C",
            "tileB": "square31D",
            "intervals": [
                [
                    20, 24,
                    22, 23
                ]
            ]
        },
        {
            "tileA": "square31A",
            "tileB": "square31B",
            "intervals": [
                [
                    20, 24,
                    19, 20
                ]
            ]
        },
        {
            "tileA": "square31C",
            "tileB": "square31D",
            "intervals": [
                [
                    20, 24,
                    20, 21
                ]
            ]
        },
        {
            "tile": "powerup-1",
            "intervals": [
                [
                    20, 21,
                    14, 15
                ]
            ]
        }
    ]
}